cython_bbox.cp39-win_amd64.pyd
cython_bbox_og-1.0.0.dist-info/LICENSE
cython_bbox_og-1.0.0.dist-info/METADATA
cython_bbox_og-1.0.0.dist-info/WHEEL
cython_bbox_og-1.0.0.dist-info/top_level.txt
cython_bbox_og-1.0.0.dist-info/RECORD
