Metadata-Version: 2.1
Name: cython-bbox-og
Version: 1.0.0
Summary: Standalone cython_bbox
Home-page: https://github.com/sr99622/cython_bbox_og
Keywords: cython_bbox_og
License-File: LICENSE
Requires-Dist: Cython
Requires-Dist: numpy
